bootstrap.py
buildout.cfg
setup.py
Products/__init__.py
Products.zope2makesite.egg-info/PKG-INFO
Products.zope2makesite.egg-info/SOURCES.txt
Products.zope2makesite.egg-info/dependency_links.txt
Products.zope2makesite.egg-info/entry_points.txt
Products.zope2makesite.egg-info/namespace_packages.txt
Products.zope2makesite.egg-info/not-zip-safe
Products.zope2makesite.egg-info/requires.txt
Products.zope2makesite.egg-info/top_level.txt
Products/zope2makesite/__init__.py