Metadata-Version: 1.0
Name: Products.zope2makesite
Version: 0.1
Summary: Makes the zope2-root a site (providing a componentregistry).
Home-page: UNKNOWN
Author: Daniel Havlik
Author-email: dh@gocept.com
License: ZPL 2.1 (http://www.zope.org/Resources/License/ZPL-2.1)
Platform: UNKNOWN
